rom.v
module rom (
	clk,
	ren,
	raddr,
	rdata
);

parameter DATA_WIDTH = 8;
parameter ADDR_WIDTH = 8;
parameter NUM_WORDS = 256;

input clk, ren;
input [ADDR_WIDTH-1:0] raddr;
output reg [DATA_WIDTH-1:0] rdata;

// Actual data storage
reg [DATA_WIDTH-1:0] mem [0:NUM_WORDS-1];

initial begin
	$readmemh("test_prog.mem", mem);
end

always @(posedge clk) begin
	if (ren)
		rdata <= mem[raddr];
end

endmodule

blockram.v
// Based on https://www.reddit.com/r/yosys/comments/5aqzyr/can_i_write_behavioral_verilog_that_infers_ice40/d9imje6/

module blockram (
	clk, wen, ren,
	waddr, raddr,
	wdata, rdata
);

parameter DATA_WIDTH = 8;
parameter ADDR_WIDTH = 8;
parameter NUM_WORDS = 256;

input clk, wen, ren;
input [ADDR_WIDTH-1:0] waddr, raddr;
input [DATA_WIDTH-1:0] wdata;
output reg [DATA_WIDTH-1:0] rdata;

// Actual data storage
reg [DATA_WIDTH-1:0] mem [0:NUM_WORDS-1];

initial begin
	$readmemh("test_ram.mem", mem);
end

always @(posedge clk) begin
	if (wen)
		mem[waddr] <= wdata;
	if (ren)
		rdata <= mem[raddr];
end

endmodule

proc.v
// set the opcodes. this takes the ascii value of
// these keys so a brainfuck program can go straight
// into memory, at the expense of a few bits.
`define INCDP   ">"
`define DECDP   "<"
`define INCDATA "+"
`define DECDATA "-"
`define OUTONE  "."
`define INONE   ","
`define CONDJMP "["
`define JMPBACK "]"

module proc (
	prog_addr,	// out: program instruction address
	prog_ren,	// out: program read enable
	data_addr,	// out: data r/w address
	data_wen,	// out: data write enable
	data_ren,	// out: data read enable
	data_wval,	// out: data write value
	stdout,		// out: data out
	stdout_en,	// out: data out enable (will be toggled when there is data)
	data_rval,	// in:  data read value
	prog_rval,	// in:  program read value (next instruction to be executed)
	clk,		// clock
	reset		// reset, active low
);

output [7:0] prog_addr;
output       prog_ren;
output [7:0] data_addr;
output 	     data_wen;
output       data_ren;
output [7:0] data_wval;
output reg [7:0] stdout = 0;
output reg stdout_en = 0;

input [7:0] data_rval;
input [7:0] prog_rval;
input       clk;
input       reset;

wire [7:0] register = data_rval;

reg [7:0] prog_addr;
reg prog_ren;
reg [7:0] data_addr;
reg data_wen;
reg data_ren;
reg [7:0] data_wval;

`define STATE_RESET			3'b000
`define STATE_FETCHDECODE	3'b001
`define STATE_EXECUTE		3'b010
`define STATE_WRITE			3'b100

reg [2:0] state;

always @(posedge clk) begin
	if (reset) begin
		stdout_en <= state[0]; // this is wrong but uhm.. seems to wake up everything. let's figure it out later!
		state <= `STATE_RESET;
		prog_ren <= 0;
		data_wen <= 0;
		data_ren <= 0;
		data_addr <= 0;
		prog_addr <= 0;
	end else begin
		//$monitor("executing: %c", prog_rval);
		case (state)
		`STATE_RESET: begin
			prog_ren <= 1;
			data_wen <= 0;
			data_ren <= 1;
			state <= `STATE_FETCHDECODE;
			end
		`STATE_FETCHDECODE: begin
			// Reads program and data, will be available in the next state
			prog_ren <= 0;
			data_wen <= 0;
			data_ren <= 0;
			stdout_en <= 0;
			state <= `STATE_EXECUTE;
			end
		`STATE_EXECUTE: begin
			// Program and data are ready to be executed
			prog_ren <= 1;
			data_wen <= 0;
			data_ren <= 1;
			prog_addr <= prog_addr + 1;
			end
		`STATE_WRITE: begin
			// Writes data, prepare for read
			prog_ren <= 1;
			data_wen <= 0;
			data_ren <= 1;
			state <= `STATE_FETCHDECODE;
			end
		default: begin
			end
		endcase

		if (state == `STATE_EXECUTE) begin
			if (prog_rval == `INCDATA || prog_rval == `DECDATA) begin
				data_wen <= 1;
				state <= `STATE_WRITE;
			end else begin
				data_wen <= 0;
				state <= `STATE_FETCHDECODE;
			end

			case (prog_rval)
				`INCDP: begin
					data_addr <= data_addr + 1;
					end
				`DECDP: begin
					data_addr <= data_addr - 1;
					end
				`INCDATA: begin
					data_wval <= register + 1;
					end
				`DECDATA: begin
					data_wval <= register - 1;
					end
				`OUTONE: begin
					stdout <= data_rval;
					stdout_en <= 1;
					//$write("%c", data_rval);
					end
				`INONE: begin
					//data <= myin;
					//data_wval <= data;
					//data_wen <= 1;
					//prog_addr <= prog_addr+1;
					//data_wen <= 0;
					end
				`CONDJMP: begin
					//data_wen <= 0;
					end
				`JMPBACK: begin
					//data_wen <= 0;
					end
				default: begin
					data_addr <= 0;
					prog_addr <= 0;
					end
			endcase //undefined opcodes not supported
		end
	end
end

endmodule

verifuck_tb.v
module bf_tb;

	reg reset;
	reg clk;

	integer i;
	initial begin
		$dumpvars;

		reset = 1;
		clk = 1;
/*
		for (i = 0; i < program_rom.NUM_WORDS; i += 1) begin
			program_rom.mem[i] <= 0;
		end

		for (i = 0; i < data_ram.NUM_WORDS; i += 1) begin
			data_ram.mem[i] <= 0;
		end

		#10 $readmemh("test_prog.mem", program_rom.mem);
		#10 $readmemh("test_ram.mem", data_ram.mem);
*/
		#30 reset = 0;
		#1000 $finish;
	end

	always #10 clk = !clk;

	wire [7:0] prog_addr;
	wire prog_ren;
	wire [7:0] data_addr;
	wire data_wen;
	wire data_ren;
	wire [7:0] data_wval;
	wire [7:0] data_rval;
	wire [7:0] prog_rval;
	wire [7:0] stdout;
	wire stdout_en;

	wire [7:0] data_temp0 = data_ram.mem[0];
	wire [7:0] data_temp1 = data_ram.mem[1];
	wire [7:0] data_temp2 = data_ram.mem[2];
	wire [7:0] data_temp3 = data_ram.mem[3];

	wire [7:0] prog_temp0 = program_rom.mem[0];
	wire [7:0] prog_temp1 = program_rom.mem[1];
	wire [7:0] prog_temp2 = program_rom.mem[2];
	wire [7:0] prog_temp3 = program_rom.mem[3];

	// "UART tx"
	always @(posedge clk) begin
		if (stdout_en)
			$write("%c", stdout);
	end

	proc myproc (
		.prog_addr(prog_addr),
		.prog_ren(prog_ren),
		.data_addr(data_addr),
		.data_wen(data_wen),
		.data_ren(data_ren),
		.data_wval(data_wval),
		.stdout(stdout),
		.stdout_en(stdout_en),
		.data_rval(data_rval),
		.prog_rval(prog_rval),
		.clk(clk),
		.reset(reset)
	);

	blockram data_ram (
		.clk(clk),
		.wen(data_wen),
		.ren(data_ren),
		.waddr(data_addr),
		.raddr(data_addr),
		.wdata(data_wval),
		.rdata(data_rval)
	);

	rom program_rom (
		.clk(clk),
		.ren(prog_ren),
		.raddr(prog_addr),
		.rdata(prog_rval)
	);

endmodule

dump.vcd
$date
	Mon Jul  2 17:25:31 2018
$end
$version
	Icarus Verilog
$end
$timescale
	1s
$end
$scope module bf_tb $end
$var wire 8 ! data_temp0 [7:0] $end
$var wire 8 " data_temp1 [7:0] $end
$var wire 8 # data_temp2 [7:0] $end
$var wire 8 $ data_temp3 [7:0] $end
$var wire 8 % prog_temp0 [7:0] $end
$var wire 8 & prog_temp1 [7:0] $end
$var wire 8 ' prog_temp2 [7:0] $end
$var wire 8 ( prog_temp3 [7:0] $end
$var wire 1 ) stdout_en $end
$var wire 8 * stdout [7:0] $end
$var wire 8 + prog_rval [7:0] $end
$var wire 1 , prog_ren $end
$var wire 8 - prog_addr [7:0] $end
$var wire 8 . data_wval [7:0] $end
$var wire 1 / data_wen $end
$var wire 8 0 data_rval [7:0] $end
$var wire 1 1 data_ren $end
$var wire 8 2 data_addr [7:0] $end
$var reg 1 3 clk $end
$var reg 1 4 reset $end
$scope module data_ram $end
$var wire 1 3 clk $end
$var wire 1 / wen $end
$var wire 8 5 wdata [7:0] $end
$var wire 8 6 waddr [7:0] $end
$var wire 1 1 ren $end
$var wire 8 7 raddr [7:0] $end
$var reg 8 8 rdata [7:0] $end
$upscope $end
$scope module myproc $end
$var wire 1 3 clk $end
$var wire 8 9 data_rval [7:0] $end
$var wire 8 : register [7:0] $end
$var wire 1 4 reset $end
$var wire 8 ; prog_rval [7:0] $end
$var reg 8 < data_addr [7:0] $end
$var reg 1 1 data_ren $end
$var reg 1 / data_wen $end
$var reg 8 = data_wval [7:0] $end
$var reg 8 > prog_addr [7:0] $end
$var reg 1 , prog_ren $end
$var reg 3 ? state [2:0] $end
$var reg 8 @ stdout [7:0] $end
$var reg 1 ) stdout_en $end
$upscope $end
$scope module program_rom $end
$var wire 1 3 clk $end
$var wire 8 A raddr [7:0] $end
$var wire 1 , ren $end
$var reg 8 B rdata [7:0] $end
$upscope $end
$upscope $end
$enddefinitions $end
#0
$dumpvars
bx B
b0 A
b0 @
b0 ?
b0 >
bx =
b0 <
bx ;
bx :
bx 9
bx 8
b0 7
b0 6
bx 5
14
13
b0 2
01
bx 0
0/
bx .
b0 -
0,
bx +
b0 *
x)
b111110 (
b101110 '
b111110 &
b101110 %
b1000100 $
b1000011 #
b1000010 "
b1000001 !
$end
#10
03
#20
0)
13
#30
03
04
#40
b1 ?
11
1,
13
#50
03
#60
b101110 +
b101110 ;
b101110 B
b1000001 :
b1000001 0
b1000001 8
b1000001 9
b10 ?
01
0,
13
#70
03
#80
1)
b1000001 *
b1000001 @
b1 ?
b1 -
b1 >
b1 A
11
1,
13
#90
03
#100
b111110 +
b111110 ;
b111110 B
b10 ?
0)
01
0,
13
#110
03
#120
b1 2
b1 6
b1 7
b1 <
b1 ?
b10 -
b10 >
b10 A
11
1,
13
#130
03
#140
b101110 +
b101110 ;
b101110 B
b1000010 :
b1000010 0
b1000010 8
b1000010 9
b10 ?
01
0,
13
#150
03
#160
1)
b1000010 *
b1000010 @
b1 ?
b11 -
b11 >
b11 A
11
1,
13
#170
03
#180
b111110 +
b111110 ;
b111110 B
b10 ?
0)
01
0,
13
#190
03
#200
b10 2
b10 6
b10 7
b10 <
b1 ?
b100 -
b100 >
b100 A
11
1,
13
#210
03
#220
b101110 +
b101110 ;
b101110 B
b1000011 :
b1000011 0
b1000011 8
b1000011 9
b10 ?
01
0,
13
#230
03
#240
1)
b1000011 *
b1000011 @
b1 ?
b101 -
b101 >
b101 A
11
1,
13
#250
03
#260
b111110 +
b111110 ;
b111110 B
b10 ?
0)
01
0,
13
#270
03
#280
b11 2
b11 6
b11 7
b11 <
b1 ?
b110 -
b110 >
b110 A
11
1,
13
#290
03
#300
b1000100 :
b1000100 0
b1000100 8
b1000100 9
b10 ?
01
0,
13
#310
03
#320
b100 2
b100 6
b100 7
b100 <
b1 ?
b111 -
b111 >
b111 A
11
1,
13
#330
03
#340
b1000101 :
b1000101 0
b1000101 8
b1000101 9
b10 ?
01
0,
13
#350
03
#360
b101 2
b101 6
b101 7
b101 <
b1 ?
b1000 -
b1000 >
b1000 A
11
1,
13
#370
03
#380
b101110 +
b101110 ;
b101110 B
b1000110 :
b1000110 0
b1000110 8
b1000110 9
b10 ?
01
0,
13
#390
03
#400
1)
b1000110 *
b1000110 @
b1 ?
b1001 -
b1001 >
b1001 A
11
1,
13
#410
03
#420
b10 ?
0)
01
0,
13
#430
03
#440
1)
b1 ?
b1010 -
b1010 >
b1010 A
11
1,
13
#450
03
#460
b10 ?
0)
01
0,
13
#470
03
#480
1)
b1 ?
b1011 -
b1011 >
b1011 A
11
1,
13
#490
03
#500
bx +
bx ;
bx B
b10 ?
0)
01
0,
13
#510
03
#520
b0 2
b0 6
b0 7
b0 <
b1 ?
b0 -
b0 >
b0 A
11
1,
13
#530
03
#540
b101110 +
b101110 ;
b101110 B
b1000001 :
b1000001 0
b1000001 8
b1000001 9
b10 ?
01
0,
13
#550
03
#560
1)
b1000001 *
b1000001 @
b1 ?
b1 -
b1 >
b1 A
11
1,
13
#570
03
#580
b111110 +
b111110 ;
b111110 B
b10 ?
0)
01
0,
13
#590
03
#600
b1 2
b1 6
b1 7
b1 <
b1 ?
b10 -
b10 >
b10 A
11
1,
13
#610
03
#620
b101110 +
b101110 ;
b101110 B
b1000010 :
b1000010 0
b1000010 8
b1000010 9
b10 ?
01
0,
13
#630
03
#640
1)
b1000010 *
b1000010 @
b1 ?
b11 -
b11 >
b11 A
11
1,
13
#650
03
#660
b111110 +
b111110 ;
b111110 B
b10 ?
0)
01
0,
13
#670
03
#680
b10 2
b10 6
b10 7
b10 <
b1 ?
b100 -
b100 >
b100 A
11
1,
13
#690
03
#700
b101110 +
b101110 ;
b101110 B
b1000011 :
b1000011 0
b1000011 8
b1000011 9
b10 ?
01
0,
13
#710
03
#720
1)
b1000011 *
b1000011 @
b1 ?
b101 -
b101 >
b101 A
11
1,
13
#730
03
#740
b111110 +
b111110 ;
b111110 B
b10 ?
0)
01
0,
13
#750
03
#760
b11 2
b11 6
b11 7
b11 <
b1 ?
b110 -
b110 >
b110 A
11
1,
13
#770
03
#780
b1000100 :
b1000100 0
b1000100 8
b1000100 9
b10 ?
01
0,
13
#790
03
#800
b100 2
b100 6
b100 7
b100 <
b1 ?
b111 -
b111 >
b111 A
11
1,
13
#810
03
#820
b1000101 :
b1000101 0
b1000101 8
b1000101 9
b10 ?
01
0,
13
#830
03
#840
b101 2
b101 6
b101 7
b101 <
b1 ?
b1000 -
b1000 >
b1000 A
11
1,
13
#850
03
#860
b101110 +
b101110 ;
b101110 B
b1000110 :
b1000110 0
b1000110 8
b1000110 9
b10 ?
01
0,
13
#870
03
#880
1)
b1000110 *
b1000110 @
b1 ?
b1001 -
b1001 >
b1001 A
11
1,
13
#890
03
#900
b10 ?
0)
01
0,
13
#910
03
#920
1)
b1 ?
b1010 -
b1010 >
b1010 A
11
1,
13
#930
03
#940
b10 ?
0)
01
0,
13
#950
03
#960
1)
b1 ?
b1011 -
b1011 >
b1011 A
11
1,
13
#970
03
#980
bx +
bx ;
bx B
b10 ?
0)
01
0,
13
#990
03
#1000
b0 2
b0 6
b0 7
b0 <
b1 ?
b0 -
b0 >
b0 A
11
1,
13
#1010
03
#1020
b101110 +
b101110 ;
b101110 B
b1000001 :
b1000001 0
b1000001 8
b1000001 9
b10 ?
01
0,
13
