baudgen.v
//-----------------------------------------------------------------------------
//-- Generacion de baudios
//-- Señal cuadrada, de periodo igual a la frecuencia de los baudios indicados
//-- El ancho del pulso positivo es de 1 ciclo de reloj
//--
//-- (c) BQ. August 2015. written by Juan Gonzalez (obijuan)
//-----------------------------------------------------------------------------
//-- GPL license
//-----------------------------------------------------------------------------
`include "baudgen.vh"

//-- ENTRADAS:
//--     -clk: Senal de reloj del sistema (12 MHZ en la iceStick)
//--     -clk_ena: Habilitacion.
//--            1. funcionamiento normal. Emitiendo pulsos
//--            0: Inicializado y parado. No se emiten pulsos
//
//-- SALIDAS:
//--     - clk_out. Señal de salida para lograr la velocidad en baudios indicada
//--                Anchura de 1 periodo de clk. SALIDA NO REGISTRADA
module baudgen(input wire clk,
               input wire clk_ena,
               output wire clk_out);

//-- Valor por defecto de la velocidad en baudios
parameter M = `B115200;

//-- Numero de bits para almacenar el divisor de baudios
localparam N = $clog2(M);

//-- Registro para implementar el contador modulo M
reg [N-1:0] divcounter = 0;

//-- Contador módulo M
always @(posedge clk)

  if (clk_ena)
    //-- Funcionamiento normal
    divcounter <= (divcounter == M - 1) ? 0 : divcounter + 1;
  else
    //-- Contador "congelado" al valor maximo
    divcounter <= M - 1;

//-- Sacar un pulso de anchura 1 ciclo de reloj si el generador
//-- esta habilitado (clk_ena == 1)
//-- en caso contrario se saca 0
assign clk_out = (divcounter == 0) ? clk_ena : 0;


endmodule

uart_tx.v
//----------------------------------------------------------------------------
//-- Unidad de transmision serie asincrona
//------------------------------------------
//-- (C) BQ. September 2015. Written by Juan Gonzalez (Obijuan)
//-- GPL license
//----------------------------------------------------------------------------
//-- Comprobado su funcionamiento a todas las velocidades estandares:
//-- 300, 600, 1200, 2400, 4800, 9600, 19200, 38400, 57600, 115200
//----------------------------------------------------------------------------
//-- Although this transmitter has been written from the scratch, it has been
//-- inspired by the one developed in the swapforth proyect by James Bowman
//--
//-- https://github.com/jamesbowman/swapforth
//--
//----------------------------------------------------------------------------
`default_nettype none

`include "baudgen.vh"

//--- Modulo de transmision serie
//--- La salida tx ESTA REGISTRADA
module uart_tx (
         input wire clk,        //-- Reloj del sistema (12MHz en ICEstick)
         input wire rstn,       //-- Reset global (activo nivel bajo)
         input wire start,      //-- Activar a 1 para transmitir
         input wire [7:0] data, //-- Byte a transmitir
         output reg tx,         //-- Salida de datos serie (hacia el PC)
         output wire ready      //-- Transmisor listo / ocupado
       );

//-- Parametro: velocidad de transmision
parameter BAUD =  `B115200;

//-- Señal de start registrada
reg start_r;

//-- Reloj para la transmision
wire clk_baud;

//-- Bitcounter
reg [3:0] bitc;

//-- Datos registrados
reg [7:0] data_r;

//--------- Microordenes
wire load;    //-- Carga del registro de desplazamiento. Puesta a 0 del
              //-- contador de bits
wire baud_en; //-- Habilitar el generador de baudios para la transmision

//-------------------------------------
//-- RUTA DE DATOS
//-------------------------------------

//-- Registrar la entrada start
//-- (para cumplir con las reglas de diseño sincrono)
always @(posedge clk)
  start_r <= start;

always @(posedge clk)
  if (start == 1 && state == IDLE)
    data_r <= data;

//-- Registro de 10 bits para almacenar la trama a enviar:
//-- 1 bit start + 8 bits datos + 1 bit stop
reg [9:0] shifter;

//-- Cuando la microorden load es 1 se carga la trama
//-- con load 0 se desplaza a la derecha y se envia un bit, al
//-- activarse la señal de clk_baud que marca el tiempo de bit
//-- Se introducen 1s por la izquierda
always @(posedge clk)
  //-- Reset
  if (rstn == 0)
    shifter <= 10'b11_1111_1111;

  //-- Modo carga
  else if (load == 1)
    shifter <= {data_r,2'b01};

  //-- Modo desplazamiento
  else if (load == 0 && clk_baud == 1)
    shifter <= {1'b1, shifter[9:1]};

//-- Contador de bits enviados
//-- Con la microorden load (=1) se hace un reset del contador
//-- con load = 0 se realiza la cuenta de los bits, al activarse
//-- clk_baud, que indica el tiempo de bit
always @(posedge clk)
  if (load == 1)
    bitc <= 0;
  else if (load == 0 && clk_baud == 1)
    bitc <= bitc + 1;

//-- Sacar por tx el bit menos significativo del registros de desplazamiento
//-- ES UNA SALIDA REGISTRADA, puesto que tx se conecta a un bus sincrono
//-- y hay que evitar que salgan pulsos espureos (glitches)
always @(posedge clk)
  tx <= shifter[0];

//-- Divisor para obtener el reloj de transmision
baudgen #(BAUD)
  BAUD0 (
    .clk(clk),
    .clk_ena(baud_en),
    .clk_out(clk_baud)
  );

//------------------------------
//-- CONTROLADOR
//------------------------------

//-- Estados del automata finito del controlador
localparam IDLE  = 0;  //-- Estado de reposo
localparam START = 1;  //-- Comienzo de transmision
localparam TRANS = 2;  //-- Estado: transmitiendo dato

//-- Estados del autómata del controlador
reg [1:0] state;

//-- Transiciones entre los estados
always @(posedge clk)

  //-- Reset del automata. Al estado inicial
  if (rstn == 0)
    state <= IDLE;

  else
    //-- Transiciones a los siguientes estados
    case (state)

      //-- Estado de reposo. Se sale cuando la señal
      //-- de start se pone a 1
      IDLE:
        if (start_r == 1)
          state <= START;
        else
          state <= IDLE;

      //-- Estado de comienzo. Prepararse para empezar
      //-- a transmitir. Duracion: 1 ciclo de reloj
      START:
        state <= TRANS;

      //-- Transmitiendo. Se esta en este estado hasta
      //-- que se hayan transmitido todos los bits pendientes
      TRANS:
        if (bitc == 11)
          state <= IDLE;
        else
          state <= TRANS;

      //-- Por defecto. NO USADO. Puesto para
      //-- cubrir todos los casos y que no se generen latches
      default:
        state <= IDLE;

    endcase

//-- Generacion de las microordenes
assign load = (state == START) ? 1 : 0;
assign baud_en = (state == IDLE) ? 0 : 1;

//-- Señal de salida. Esta a 1 cuando estamos en reposo (listos
//-- para transmitir). En caso contrario esta a 0
assign ready = (state == IDLE) ? 1 : 0;

endmodule

rom.v
module rom (
	clk,
	ren,
	raddr,
	rdata
);

parameter DATA_WIDTH = 8;
parameter ADDR_WIDTH = 8;
parameter NUM_WORDS = 256;

input clk, ren;
input [ADDR_WIDTH-1:0] raddr;
output reg [DATA_WIDTH-1:0] rdata;

// Actual data storage
reg [DATA_WIDTH-1:0] mem [0:NUM_WORDS-1];

initial begin
	$readmemh("test_prog.mem", mem);
end

always @(posedge clk) begin
	if (ren)
		rdata <= mem[raddr];
end

endmodule

blockram.v
// Based on https://www.reddit.com/r/yosys/comments/5aqzyr/can_i_write_behavioral_verilog_that_infers_ice40/d9imje6/

module blockram (
	clk, wen, ren,
	waddr, raddr,
	wdata, rdata
);

parameter DATA_WIDTH = 8;
parameter ADDR_WIDTH = 8;
parameter NUM_WORDS = 256;

input clk, wen, ren;
input [ADDR_WIDTH-1:0] waddr, raddr;
input [DATA_WIDTH-1:0] wdata;
output reg [DATA_WIDTH-1:0] rdata;

// Actual data storage
reg [DATA_WIDTH-1:0] mem [0:NUM_WORDS-1];

// Make the first 4 words visible in gtkwave
wire [DATA_WIDTH-1:0] mem0 = mem[0];
wire [DATA_WIDTH-1:0] mem1 = mem[1];
wire [DATA_WIDTH-1:0] mem2 = mem[2];
wire [DATA_WIDTH-1:0] mem3 = mem[3];

// integer i;
initial begin
	// for (i = 0; i < NUM_WORDS; i = i + 1)
	// 	mem[i] = 0;
	$readmemh("test_ram.mem", mem);
end

always @(posedge clk) begin
	if (wen)
		mem[waddr] <= wdata;
	if (ren)
		rdata <= mem[raddr];
end

endmodule

proc.v
// Used https://github.com/jackcarrozzo/brainfuck-processor as a baseline

`define INCDP   ">"
`define DECDP   "<"
`define INCDATA "+"
`define DECDATA "-"
`define OUTONE  "."
`define INONE   ","
`define CONDJMP "["
`define JMPBACK "]"

module proc (
	prog_addr,	// out: program instruction address
	prog_ren,	// out: program read enable
	data_addr,	// out: data r/w address
	data_wen,	// out: data write enable
	data_ren,	// out: data read enable
	data_wval,	// out: data write value
	stdout,		// out: data out
	stdout_en,	// out: data out enable (will be toggled when there is data)
	data_rval,	// in:  data read value
	prog_rval,	// in:  program read value (next instruction to be executed)
	clk,		// clock
	reset		// reset, active low
);

output [7:0] prog_addr;
output       prog_ren;
output [7:0] data_addr;
output 	     data_wen;
output       data_ren;
output [7:0] data_wval;
output reg [7:0] stdout = 0;
output reg stdout_en = 0;

input [7:0] data_rval;
input [7:0] prog_rval;
input       clk;
input       reset;

wire [7:0] register = data_rval;

reg [7:0] prog_addr;
reg prog_ren;
reg [7:0] data_addr;
reg data_wen;
reg data_ren;
reg [7:0] data_wval = 0;

`define STATE_RESET			3'b000
`define STATE_FETCHDECODE	3'b001
`define STATE_EXECUTE		3'b010
`define STATE_WRITE			3'b100

reg [2:0] state = `STATE_RESET;

always @(posedge clk) begin
	if (reset) begin
		state <= `STATE_RESET;
		prog_ren <= 0;
		data_wen <= 0;
		data_ren <= 0;
		data_addr <= 0;
		prog_addr <= 0;
	end else begin
		//$monitor("executing: %c", prog_rval);
		case (state)
		`STATE_RESET: begin
			prog_ren <= 1;
			data_wen <= 0;
			data_ren <= 1;
			state <= `STATE_FETCHDECODE;
			end
		`STATE_FETCHDECODE: begin
			// Reads program and data, will be available in the next state
			prog_ren <= 0;
			data_wen <= 0;
			data_ren <= 0;
			stdout_en <= 0;
			state <= `STATE_EXECUTE;
			end
		`STATE_EXECUTE: begin
			// Program and data are ready to be executed
			prog_ren <= 1;
			data_wen <= 0;
			data_ren <= 1;
			prog_addr <= prog_addr + 1;
			end
		`STATE_WRITE: begin
			// Writes data, prepare for read
			prog_ren <= 1;
			data_wen <= 0;
			data_ren <= 1;
			state <= `STATE_FETCHDECODE;
			end
		default: begin
			end
		endcase

		if (state == `STATE_EXECUTE) begin
			if (prog_rval == `INCDATA || prog_rval == `DECDATA) begin
				data_wen <= 1;
				state <= `STATE_WRITE;
			end else begin
				data_wen <= 0;
				state <= `STATE_FETCHDECODE;
			end

			case (prog_rval)
				`INCDP: begin
					data_addr <= data_addr + 1;
					end
				`DECDP: begin
					data_addr <= data_addr - 1;
					end
				`INCDATA: begin
					data_wval <= register + 1;
					end
				`DECDATA: begin
					data_wval <= register - 1;
					end
				`OUTONE: begin
					stdout <= data_rval;
					stdout_en <= 1;
					//$write("%c", data_rval);
					end
				`INONE: begin
					//data <= myin;
					//data_wval <= data;
					//data_wen <= 1;
					//prog_addr <= prog_addr+1;
					//data_wen <= 0;
					end
				`CONDJMP: begin
					//data_wen <= 0;
					end
				`JMPBACK: begin
					//data_wen <= 0;
					end
				default: begin
					data_addr <= 0;
					prog_addr <= 0;
					end
			endcase //undefined opcodes not supported
		end
	end
end

endmodule

verifuck_tb.v
module bf_tb;

	reg reset;
	reg clk;
	always #10 clk = !clk;

	integer i;
	initial begin
		$dumpvars;

		reset = 1;
		clk = 1;

		#30 reset = 0;
		#1000 $finish;
	end

	wire [7:0] prog_addr;
	wire prog_ren;
	wire [7:0] data_addr;
	wire data_wen;
	wire data_ren;
	wire [7:0] data_wval;
	wire [7:0] data_rval;
	wire [7:0] prog_rval;
	wire [7:0] stdout;
	wire stdout_en;

	wire [7:0] data_temp0 = data_ram.mem[0];
	wire [7:0] data_temp1 = data_ram.mem[1];
	wire [7:0] data_temp2 = data_ram.mem[2];
	wire [7:0] data_temp3 = data_ram.mem[3];

	wire [7:0] prog_temp0 = program_rom.mem[0];
	wire [7:0] prog_temp1 = program_rom.mem[1];
	wire [7:0] prog_temp2 = program_rom.mem[2];
	wire [7:0] prog_temp3 = program_rom.mem[3];

	// "UART tx"
	always @(posedge clk) begin
		if (stdout_en)
			$write("%c", stdout);
	end

	proc myproc (
		.prog_addr(prog_addr),
		.prog_ren(prog_ren),
		.data_addr(data_addr),
		.data_wen(data_wen),
		.data_ren(data_ren),
		.data_wval(data_wval),
		.stdout(stdout),
		.stdout_en(stdout_en),
		.data_rval(data_rval),
		.prog_rval(prog_rval),
		.clk(clk),
		.reset(reset)
	);

	blockram data_ram (
		.clk(clk),
		.wen(data_wen),
		.ren(data_ren),
		.waddr(data_addr),
		.raddr(data_addr),
		.wdata(data_wval),
		.rdata(data_rval)
	);

	rom program_rom (
		.clk(clk),
		.ren(prog_ren),
		.raddr(prog_addr),
		.rdata(prog_rval)
	);

endmodule

dump.vcd
$date
	Mon Jul  2 18:30:47 2018
$end
$version
	Icarus Verilog
$end
$timescale
	1s
$end
$scope module bf_tb $end
$var wire 8 ! data_temp0 [7:0] $end
$var wire 8 " data_temp1 [7:0] $end
$var wire 8 # data_temp2 [7:0] $end
$var wire 8 $ data_temp3 [7:0] $end
$var wire 8 % prog_temp0 [7:0] $end
$var wire 8 & prog_temp1 [7:0] $end
$var wire 8 ' prog_temp2 [7:0] $end
$var wire 8 ( prog_temp3 [7:0] $end
$var wire 1 ) stdout_en $end
$var wire 8 * stdout [7:0] $end
$var wire 8 + prog_rval [7:0] $end
$var wire 1 , prog_ren $end
$var wire 8 - prog_addr [7:0] $end
$var wire 8 . data_wval [7:0] $end
$var wire 1 / data_wen $end
$var wire 8 0 data_rval [7:0] $end
$var wire 1 1 data_ren $end
$var wire 8 2 data_addr [7:0] $end
$var reg 1 3 clk $end
$var reg 1 4 reset $end
$scope module data_ram $end
$var wire 1 3 clk $end
$var wire 1 / wen $end
$var wire 8 5 wdata [7:0] $end
$var wire 8 6 waddr [7:0] $end
$var wire 1 1 ren $end
$var wire 8 7 raddr [7:0] $end
$var reg 8 8 rdata [7:0] $end
$upscope $end
$scope module myproc $end
$var wire 1 3 clk $end
$var wire 8 9 data_rval [7:0] $end
$var wire 8 : register [7:0] $end
$var wire 1 4 reset $end
$var wire 8 ; prog_rval [7:0] $end
$var reg 8 < data_addr [7:0] $end
$var reg 1 1 data_ren $end
$var reg 1 / data_wen $end
$var reg 8 = data_wval [7:0] $end
$var reg 8 > prog_addr [7:0] $end
$var reg 1 , prog_ren $end
$var reg 3 ? state [2:0] $end
$var reg 8 @ stdout [7:0] $end
$var reg 1 ) stdout_en $end
$upscope $end
$scope module program_rom $end
$var wire 1 3 clk $end
$var wire 8 A raddr [7:0] $end
$var wire 1 , ren $end
$var reg 8 B rdata [7:0] $end
$upscope $end
$upscope $end
$scope module uart_tx $end
$var wire 1 C clk $end
$var wire 8 D data [7:0] $end
$var wire 1 E rstn $end
$var wire 1 F start $end
$var wire 1 G ready $end
$var wire 1 H load $end
$var wire 1 I clk_baud $end
$var wire 1 J baud_en $end
$var reg 4 K bitc [3:0] $end
$var reg 8 L data_r [7:0] $end
$var reg 10 M shifter [9:0] $end
$var reg 1 N start_r $end
$var reg 2 O state [1:0] $end
$var reg 1 P tx $end
$scope module BAUD0 $end
$var wire 1 C clk $end
$var wire 1 J clk_ena $end
$var wire 1 I clk_out $end
$var reg 7 Q divcounter [6:0] $end
$upscope $end
$upscope $end
$enddefinitions $end
#0
$dumpvars
b0 Q
xP
bx O
xN
bx M
bx L
bx K
xJ
xI
xH
xG
zF
zE
bz D
zC
bx B
b0 A
b0 @
b0 ?
b0 >
b0 =
b0 <
bx ;
bx :
bx 9
bx 8
b0 7
b0 6
b0 5
14
13
b0 2
01
bx 0
0/
b0 .
b0 -
0,
bx +
b0 *
0)
b111110 (
b101110 '
b111110 &
b101110 %
b1000100 $
b1000011 #
b1000010 "
b1000001 !
$end
#10
03
#20
13
#30
03
04
#40
b1 ?
11
1,
13
#50
03
#60
b101110 +
b101110 ;
b101110 B
b1000001 :
b1000001 0
b1000001 8
b1000001 9
b10 ?
01
0,
13
#70
03
#80
1)
b1000001 *
b1000001 @
b1 ?
b1 -
b1 >
b1 A
11
1,
13
#90
03
#100
b111110 +
b111110 ;
b111110 B
b10 ?
0)
01
0,
13
#110
03
#120
b1 2
b1 6
b1 7
b1 <
b1 ?
b10 -
b10 >
b10 A
11
1,
13
#130
03
#140
b101110 +
b101110 ;
b101110 B
b1000010 :
b1000010 0
b1000010 8
b1000010 9
b10 ?
01
0,
13
#150
03
#160
1)
b1000010 *
b1000010 @
b1 ?
b11 -
b11 >
b11 A
11
1,
13
#170
03
#180
b111110 +
b111110 ;
b111110 B
b10 ?
0)
01
0,
13
#190
03
#200
b10 2
b10 6
b10 7
b10 <
b1 ?
b100 -
b100 >
b100 A
11
1,
13
#210
03
#220
b101110 +
b101110 ;
b101110 B
b1000011 :
b1000011 0
b1000011 8
b1000011 9
b10 ?
01
0,
13
#230
03
#240
1)
b1000011 *
b1000011 @
b1 ?
b101 -
b101 >
b101 A
11
1,
13
#250
03
#260
b111110 +
b111110 ;
b111110 B
b10 ?
0)
01
0,
13
#270
03
#280
b11 2
b11 6
b11 7
b11 <
b1 ?
b110 -
b110 >
b110 A
11
1,
13
#290
03
#300
b1000100 :
b1000100 0
b1000100 8
b1000100 9
b10 ?
01
0,
13
#310
03
#320
b100 2
b100 6
b100 7
b100 <
b1 ?
b111 -
b111 >
b111 A
11
1,
13
#330
03
#340
b1000101 :
b1000101 0
b1000101 8
b1000101 9
b10 ?
01
0,
13
#350
03
#360
b101 2
b101 6
b101 7
b101 <
b1 ?
b1000 -
b1000 >
b1000 A
11
1,
13
#370
03
#380
b101110 +
b101110 ;
b101110 B
b1000110 :
b1000110 0
b1000110 8
b1000110 9
b10 ?
01
0,
13
#390
03
#400
1)
b1000110 *
b1000110 @
b1 ?
b1001 -
b1001 >
b1001 A
11
1,
13
#410
03
#420
b10 ?
0)
01
0,
13
#430
03
#440
1)
b1 ?
b1010 -
b1010 >
b1010 A
11
1,
13
#450
03
#460
b10 ?
0)
01
0,
13
#470
03
#480
1)
b1 ?
b1011 -
b1011 >
b1011 A
11
1,
13
#490
03
#500
bx +
bx ;
bx B
b10 ?
0)
01
0,
13
#510
03
#520
b0 2
b0 6
b0 7
b0 <
b1 ?
b0 -
b0 >
b0 A
11
1,
13
#530
03
#540
b101110 +
b101110 ;
b101110 B
b1000001 :
b1000001 0
b1000001 8
b1000001 9
b10 ?
01
0,
13
#550
03
#560
1)
b1000001 *
b1000001 @
b1 ?
b1 -
b1 >
b1 A
11
1,
13
#570
03
#580
b111110 +
b111110 ;
b111110 B
b10 ?
0)
01
0,
13
#590
03
#600
b1 2
b1 6
b1 7
b1 <
b1 ?
b10 -
b10 >
b10 A
11
1,
13
#610
03
#620
b101110 +
b101110 ;
b101110 B
b1000010 :
b1000010 0
b1000010 8
b1000010 9
b10 ?
01
0,
13
#630
03
#640
1)
b1000010 *
b1000010 @
b1 ?
b11 -
b11 >
b11 A
11
1,
13
#650
03
#660
b111110 +
b111110 ;
b111110 B
b10 ?
0)
01
0,
13
#670
03
#680
b10 2
b10 6
b10 7
b10 <
b1 ?
b100 -
b100 >
b100 A
11
1,
13
#690
03
#700
b101110 +
b101110 ;
b101110 B
b1000011 :
b1000011 0
b1000011 8
b1000011 9
b10 ?
01
0,
13
#710
03
#720
1)
b1000011 *
b1000011 @
b1 ?
b101 -
b101 >
b101 A
11
1,
13
#730
03
#740
b111110 +
b111110 ;
b111110 B
b10 ?
0)
01
0,
13
#750
03
#760
b11 2
b11 6
b11 7
b11 <
b1 ?
b110 -
b110 >
b110 A
11
1,
13
#770
03
#780
b1000100 :
b1000100 0
b1000100 8
b1000100 9
b10 ?
01
0,
13
#790
03
#800
b100 2
b100 6
b100 7
b100 <
b1 ?
b111 -
b111 >
b111 A
11
1,
13
#810
03
#820
b1000101 :
b1000101 0
b1000101 8
b1000101 9
b10 ?
01
0,
13
#830
03
#840
b101 2
b101 6
b101 7
b101 <
b1 ?
b1000 -
b1000 >
b1000 A
11
1,
13
#850
03
#860
b101110 +
b101110 ;
b101110 B
b1000110 :
b1000110 0
b1000110 8
b1000110 9
b10 ?
01
0,
13
#870
03
#880
1)
b1000110 *
b1000110 @
b1 ?
b1001 -
b1001 >
b1001 A
11
1,
13
#890
03
#900
b10 ?
0)
01
0,
13
#910
03
#920
1)
b1 ?
b1010 -
b1010 >
b1010 A
11
1,
13
#930
03
#940
b10 ?
0)
01
0,
13
#950
03
#960
1)
b1 ?
b1011 -
b1011 >
b1011 A
11
1,
13
#970
03
#980
bx +
bx ;
bx B
b10 ?
0)
01
0,
13
#990
03
#1000
b0 2
b0 6
b0 7
b0 <
b1 ?
b0 -
b0 >
b0 A
11
1,
13
#1010
03
#1020
b101110 +
b101110 ;
b101110 B
b1000001 :
b1000001 0
b1000001 8
b1000001 9
b10 ?
01
0,
13
